clairql_parser.cpython-311-darwin.so
clairql_parser-1.0.45.dist-info/RECORD
clairql_parser-1.0.45.dist-info/WHEEL
clairql_parser-1.0.45.dist-info/top_level.txt
clairql_parser-1.0.45.dist-info/METADATA
clairql_parser.dylibs/libantlr4-runtime.4.13.2.dylib
